vhh_stc/Configuration.py
vhh_stc/CustomTransforms.py
vhh_stc/Datasets.py
vhh_stc/Models.py
vhh_stc/STC.py
vhh_stc/Shot.py
vhh_stc/Video.py
vhh_stc/__init__.py
vhh_stc/utils.py
vhh_stc-1.3.0.dist-info/LICENSE
vhh_stc-1.3.0.dist-info/METADATA
vhh_stc-1.3.0.dist-info/WHEEL
vhh_stc-1.3.0.dist-info/top_level.txt
vhh_stc-1.3.0.dist-info/RECORD
