Metadata-Version: 2.1
Name: vhh-stc
Version: 1.3.0
Summary: Shot Type Classification Package
Home-page: https://github.com/dahe-cvl/vhh_stc
Author: Daniel Helm
Author-email: daniel.helm@tuwien.ac.at
License-File: LICENSE
Requires-Dist: Pillow
Requires-Dist: opencv-python
Requires-Dist: matplotlib
Requires-Dist: scipy
Requires-Dist: PyYAML
Requires-Dist: numpy
Requires-Dist: h5py
Requires-Dist: scikit-learn (==0.22.2)
Requires-Dist: Sphinx
Requires-Dist: sphinxcontrib-bibtex
Requires-Dist: sphinxcontrib-autoyaml
